docsclient/__init__.py
docsclient/_version.py
docsclient/client.py
docsclient-0.0.10.dist-info/DESCRIPTION.rst
docsclient-0.0.10.dist-info/METADATA
docsclient-0.0.10.dist-info/RECORD
docsclient-0.0.10.dist-info/WHEEL
docsclient-0.0.10.dist-info/metadata.json
docsclient-0.0.10.dist-info/top_level.txt
